_wagyu.cpython-39-x86_64-linux-gnu.so
wagyu-0.2.2.dist-info/WHEEL
wagyu-0.2.2.dist-info/LICENSE
wagyu-0.2.2.dist-info/RECORD
wagyu-0.2.2.dist-info/top_level.txt
wagyu-0.2.2.dist-info/METADATA
wagyu/wagyu.py
wagyu/polygon.py
wagyu/local_minimum.py
wagyu/box.py
wagyu/point.py
wagyu/bound.py
wagyu/hints.py
wagyu/point_node.py
wagyu/__init__.py
wagyu/linear_ring.py
wagyu/ring_manager.py
wagyu/ring.py
wagyu/enums.py
wagyu/utils.py
wagyu/bubble_sort.py
wagyu/edge.py
wagyu/intersect_node.py
